yelp_reviews_scraper/__init__.py
yelp_reviews_scraper/client.py
yelp_reviews_scraper/utils.py
yelp_reviews_scraper-0.0.1.dist-info/LICENSE
yelp_reviews_scraper-0.0.1.dist-info/METADATA
yelp_reviews_scraper-0.0.1.dist-info/WHEEL
yelp_reviews_scraper-0.0.1.dist-info/top_level.txt
yelp_reviews_scraper-0.0.1.dist-info/RECORD
